vlc-radio/__init__.py
vlc-radio/__main__.py
vlcradio/__init__.py
vlcradio/__main__.py
vlcradio-0.0.3.dist-info/LICENSE
vlcradio-0.0.3.dist-info/METADATA
vlcradio-0.0.3.dist-info/WHEEL
vlcradio-0.0.3.dist-info/top_level.txt
vlcradio-0.0.3.dist-info/RECORD
