Metadata-Version: 2.1
Name: vlcradio
Version: 0.0.3
Summary: export VLC metadata
Home-page: https://github.com/MartinBarker/VLC-Radio
Author: martinbarker99
Author-email: martinbarker99@gmail.com
License: UNKNOWN
Platform: UNKNOWN
Classifier: Programming Language :: Python :: 3
Classifier: License :: OSI Approved :: MIT License
Classifier: Operating System :: OS Independent
